{"cameraMode":{"drawMode":0,"name":"Shaded","section":"Shading Mode"},"sceneLighting":false,"audioPlay":false,"sceneViewState":{"showFog":true,"showMaterialUpdate":false,"showSkybox":false,"showFlares":true,"showImageEffects":true,"showParticleSystems":true},"in2DMode":false,"pivot":{"x":4.828939914703369,"y":-1.8663901090621949,"z":-5.955039024353027},"rotation":{"x":-0.2678319215774536,"y":-0.37562185525894167,"z":0.11434412747621536,"w":-0.8798294067382813},"size":27.762056350708009,"orthographic":false}